bin/__init__.py
markdata/__init__.py
markdata/__version__.py
markdata/cli.py
markdata/converters.py
markdata/directives.py
tests/block/__init__.py
tests/ditaa/__init__.py
tests/output/__init__.py
markdata-0.5.2.dist-info/LICENSE
markdata-0.5.2.dist-info/METADATA
markdata-0.5.2.dist-info/WHEEL
markdata-0.5.2.dist-info/entry_points.txt
markdata-0.5.2.dist-info/top_level.txt
markdata-0.5.2.dist-info/RECORD
