Metadata-Version: 2.1
Name: markdata
Version: 0.5.2
Summary: An extensible, parser-agnostic 'include' directive for Markdown.
Home-page: https://github.com/errata-ai/markdata
Author: Joseph Kato
Author-email: joseph@jdkato.io
License: MIT
Platform: UNKNOWN
Classifier: License :: OSI Approved :: MIT License
Classifier: Programming Language :: Python
Classifier: Programming Language :: Python :: 3
Classifier: Programming Language :: Python :: 3.6
Requires-Python: >=3.6.0
Requires-Dist: pyyaml
Requires-Dist: tabulate
Requires-Dist: click
Requires-Dist: python-frontmatter
